pyschemetranspiler/__init__.py
pyschemetranspiler/__main__.py
pyschemetranspiler/builder.py
pyschemetranspiler/coloring.py
pyschemetranspiler/converter.py
pyschemetranspiler/exceptions.py
pyschemetranspiler/extraCodes.py
pyschemetranspiler/parser.py
pyschemetranspiler/run.py
pyschemetranspiler/shared.py
pyschemetranspiler-1.3.dist-info/LICENSE
pyschemetranspiler-1.3.dist-info/METADATA
pyschemetranspiler-1.3.dist-info/WHEEL
pyschemetranspiler-1.3.dist-info/entry_points.txt
pyschemetranspiler-1.3.dist-info/top_level.txt
pyschemetranspiler-1.3.dist-info/RECORD
