Metadata-Version: 2.1
Name: pyschemetranspiler
Version: 1.3
Summary: Transpile simple Python to Scheme(Racket)
Home-page: https://github.com/Coronon/PySchemeTranspiler
Author: Rubin Raithel
Author-email: dev@rubinraithel.de
License: UNKNOWN
Platform: UNKNOWN
Classifier: Programming Language :: Python :: 3
Classifier: License :: OSI Approved :: GNU General Public License v3 (GPLv3)
Classifier: Operating System :: OS Independent
Requires-Python: == 3.8.*
License-File: LICENSE
